{"cameraMode":{"drawMode":0,"name":"Shaded","section":"Shading Mode"},"sceneLighting":false,"audioPlay":false,"sceneViewState":{"m_AlwaysRefresh":false,"showFog":true,"showSkybox":false,"showFlares":true,"showImageEffects":true,"showParticleSystems":true,"showVisualEffectGraphs":true,"m_FxEnabled":true},"in2DMode":false,"pivot":{"x":-0.18707270920276643,"y":0.8122140169143677,"z":5.415309906005859},"rotation":{"x":0.027786388993263246,"y":0.1002669557929039,"z":0.005678652785718441,"w":-0.9952954649925232},"size":0.5486994385719299,"orthographic":false}